jellyjoin/__init__.py
jellyjoin/_join.py
jellyjoin/plots.py
jellyjoin/similarity.py
jellyjoin/strategy.py
jellyjoin/typing.py
jellyjoin-0.2.7.dist-info/licenses/LICENSE.txt
jellyjoin-0.2.7.dist-info/METADATA
jellyjoin-0.2.7.dist-info/WHEEL
jellyjoin-0.2.7.dist-info/top_level.txt
jellyjoin-0.2.7.dist-info/RECORD
