Metadata-Version: 2.4
Name: jellyjoin
Version: 0.2.7
Summary: Utilities for dataset similarity and joins
Author-email: Oran Looney <olooney@gmail.com>
License-Expression: MIT
Project-URL: Homepage, https://github.com/olooney/jellyjoin
Project-URL: Repository, https://github.com/olooney/jellyjoin
Classifier: Programming Language :: Python :: 3
Classifier: Programming Language :: Python :: 3.10
Classifier: Programming Language :: Python :: 3.11
Classifier: Programming Language :: Python :: 3.12
Classifier: Programming Language :: Python :: 3.13
Classifier: Programming Language :: Python :: 3.14
Classifier: Operating System :: OS Independent
Classifier: Intended Audience :: Developers
Classifier: Topic :: Scientific/Engineering :: Information Analysis
Requires-Python: >=3.10
License-File: LICENSE.txt
Requires-Dist: jellyfish>=1.1.0
Requires-Dist: numpy>=1.24.4
Requires-Dist: pandas>=2.1.2
Requires-Dist: scipy>=1.10.0
Requires-Dist: typing_extensions>=4.12.2
Provides-Extra: dev
Requires-Dist: build; extra == "dev"
Requires-Dist: matplotlib>=3.8.4; extra == "dev"
Requires-Dist: openai>=1.61.1; extra == "dev"
Requires-Dist: tiktoken>=0.7.0; extra == "dev"
Requires-Dist: nomic[local]>=3.6.0; extra == "dev"
Requires-Dist: ollama>=0.1.9; extra == "dev"
Requires-Dist: pre-commit; extra == "dev"
Requires-Dist: pytest; extra == "dev"
Requires-Dist: pytest-cov>=7.0.0; extra == "dev"
Requires-Dist: python-dotenv; extra == "dev"
Requires-Dist: ruff; extra == "dev"
Requires-Dist: twine; extra == "dev"
Provides-Extra: test
Requires-Dist: pytest>=8.3.3; extra == "test"
Requires-Dist: python-dotenv>=1.0.1; extra == "test"
Requires-Dist: pytest-cov>=7.0.0; extra == "test"
Requires-Dist: matplotlib>=3.8.4; extra == "test"
Provides-Extra: extra
Requires-Dist: matplotlib>=3.5.3; extra == "extra"
Requires-Dist: openai>=1.61.1; extra == "extra"
Requires-Dist: tiktoken>=0.7.0; extra == "extra"
Requires-Dist: nomic[local]>=3.6.0; extra == "extra"
Requires-Dist: ollama>=0.1.9; extra == "extra"
Dynamic: license-file
